unzipmbcs.py
unzipmbcs-0.2.0.dist-info/LICENSE.txt
unzipmbcs-0.2.0.dist-info/METADATA
unzipmbcs-0.2.0.dist-info/WHEEL
unzipmbcs-0.2.0.dist-info/entry_points.txt
unzipmbcs-0.2.0.dist-info/top_level.txt
unzipmbcs-0.2.0.dist-info/RECORD
