Metadata-Version: 2.1
Name: unzipmbcs
Version: 0.2.0
Summary: UnZip for non-UTF8 encoding such as cp949, sjis, gbk, euc-kr, euc-jp, and gb2312
Author-email: Joo-Won Jung <sanori@gmail.com>
Project-URL: repository, https://github.com/sanori/unzip-mbcs
Keywords: unzip,pkzip,non-UTF8,mbcs,cp949,sjis,shift_jis,gbk,gb18030
Classifier: Development Status :: 3 - Alpha
Classifier: License :: OSI Approved :: Apache Software License
Classifier: Programming Language :: Python :: 2
Classifier: Programming Language :: Python :: 3
License-File: LICENSE.txt
